{
  "firingMode": "Firing Mode",
  "rof": "Rate of fire",
  "penetrationLevel": "Penetration Level",
  "adsTime": "ADS Time",
  "adsZoom": "ADS Zoom%",
  "bht": "Breath Hold Time",
  "bsa": "Bullet Spread Accuracy",
  "bulletVelocity": "Bullet Velocity",
  "bulletsPerShot": "Bullets Per Shot",
  "burstRpmDelay": "Burst Delay",
  "hipfireSpread": "Hipfire Spread",
  "magazineSize": "Magazine Size",
  "reserve": "Magazine Reserve",
  "reloadTime": "Reload Time",
  "reloadCancel": "Reload Cancel",
  "ReloadTimeEmpty": "Empty Reload Time",
  "reloadCancelEmpty": "Empty Reload Cancel",
  "stf": "Sprint to fire",
  "raiseTime": "Raise Time",
  "dropTime": "Drop Time",
  "sprinting": "Sprinting Speed",
  "walking": "Movement Speed"
}
